{
	"instance" : {
		"initialize" : "YuriyTymchuk 3/4/2016 16:51",
		"showErrors" : "YuriyTymchuk 3/4/2016 17:00",
		"showErrors:" : "YuriyTymchuk 3/4/2016 17:00"
	},
	"class" : {
		"reGroupSettingsOn:" : "YuriyTymchuk 6/14/2016 15:21",
		"showErrors" : "YuriyTymchuk 3/4/2016 17:06",
		"showErrorsSettingsOn:" : "YuriyTymchuk 6/14/2016 15:21",
		"cleanUp" : "YuriyTymchuk 3/4/2016 17:00",
		"resetButtonSettingsOn:" : "YuriyTymchuk 6/14/2016 15:28",
		"showErrors:" : "YuriyTymchuk 3/4/2016 17:00",
		"uniqueInstance" : "YuriyTymchuk 3/4/2016 16:49"
	}
}